foreva_ai/__init__.py
foreva_ai/agent.py
foreva_ai/cli.py
foreva_ai/client.py
foreva_ai/config.py
foreva_ai/exceptions.py
foreva_ai/types.py
foreva_ai/examples/quick_start.py
foreva_ai-0.0.7.dist-info/licenses/LICENSE
foreva_ai-0.0.7.dist-info/METADATA
foreva_ai-0.0.7.dist-info/WHEEL
foreva_ai-0.0.7.dist-info/entry_points.txt
foreva_ai-0.0.7.dist-info/top_level.txt
foreva_ai-0.0.7.dist-info/RECORD
